lauritzen_hoffman/__init__.py
lauritzen_hoffman/functions.py
lauritzen_hoffman/linear_rate.py
lauritzen_hoffman/load.py
lauritzen_hoffman/log_functions.py
lauritzen_hoffman-1.0.dist-info/METADATA
lauritzen_hoffman-1.0.dist-info/WHEEL
lauritzen_hoffman-1.0.dist-info/entry_points.txt
lauritzen_hoffman-1.0.dist-info/top_level.txt
lauritzen_hoffman-1.0.dist-info/RECORD
